gui_app/__init__.py
gui_app/gui_app.py
noplaintext/__init__.py
noplaintext/crypto_utils.py
noplaintext_Sluke950-0.3.0.dist-info/METADATA
noplaintext_Sluke950-0.3.0.dist-info/WHEEL
noplaintext_Sluke950-0.3.0.dist-info/top_level.txt
noplaintext_Sluke950-0.3.0.dist-info/RECORD
