Metadata-Version: 2.1
Name: noplaintext_Sluke950
Version: 0.3.0
Summary: An application for generating and managing encryption keys and encrypting/decrypting messages.
Author-email: Luke Shuttleworth <Sluke950@gmail.com>
Project-URL: Homepage, https://github.com/Sluke950/noplaintext
Project-URL: Issues, https://github.com/Sluke950/noplaintext/issues
Classifier: Programming Language :: Python :: 3
Classifier: License :: OSI Approved :: MIT License
Classifier: Operating System :: OS Independent
Requires-Python: >=3.8
Requires-Dist: cryptography>=39.0.1
